datadatalib/__init__.py
datadatalib/plot/__init__.py
datadatalib/plot/plot.py
datadatalib/preprocess/__init__.py
datadatalib/preprocess/preprocess.py
datadatalib-0.2.2.dist-info/METADATA
datadatalib-0.2.2.dist-info/WHEEL
datadatalib-0.2.2.dist-info/top_level.txt
datadatalib-0.2.2.dist-info/RECORD
