Metadata-Version: 2.1
Name: datadatalib
Version: 0.2.2
Summary: DataData library
Home-page: UNKNOWN
Author: DataData
Author-email: UNKNOWN
License: UNKNOWN
Platform: UNKNOWN
